gies/__init__.py
gies/main.py
gies/scratch.py
gies/utils.py
gies/scores/__init__.py
gies/scores/decomposable_score.py
gies/scores/exp_gauss_int_l0_pen.py
gies/scores/gauss_int_l0_pen.py
gies/scores/gauss_obs_l0_pen.py
gies/scores/infinite_score.py
gies/scores/log_likelihood.py
gies/scores/log_likelihood_means.py
gies/test/__init__.py
gies/test/test_decomposable_score.py
gies/test/test_gauss_bic.py
gies/test/test_int_score.py
gies/test/test_operators.py
gies/test/test_pdag_to_cpdag.py
gies/test/test_utils.py
gies/test/test_vs_R.py
gies-0.0.3.dist-info/LICENSE.txt
gies-0.0.3.dist-info/METADATA
gies-0.0.3.dist-info/WHEEL
gies-0.0.3.dist-info/top_level.txt
gies-0.0.3.dist-info/RECORD
