Metadata-Version: 2.2
Name: gies
Version: 0.0.3
Summary: Python implementation of the GIES algorithm for causal discovery
Home-page: https://github.com/juangamella/gies
Author: Juan L. Gamella, Olga Kolotuhina
Author-email: juangamella@gmail.com
License: BSD 3-Clause License
License-File: LICENSE.txt
Requires-Dist: numpy>=1.15.0
Dynamic: author
Dynamic: author-email
Dynamic: description
Dynamic: description-content-type
Dynamic: home-page
Dynamic: license
Dynamic: requires-dist
Dynamic: summary
